{"WRIT002": {"course_desc": "Composition and Research", "offered": false, "url": "https://www.layuplist.com/course/3009", "distribs": []}, "WRIT003": {"course_desc": "Composition and Research", "offered": false, "url": "https://www.layuplist.com/course/3010", "distribs": []}, "WRIT005": {"course_desc": "Expository Writing", "offered": true, "url": "https://www.layuplist.com/course/3011", "distribs": []}, "WRIT007.01": {"course_desc": "Religion and Literature", "offered": false, "url": "https://www.layuplist.com/course/3123", "distribs": ["LIT"]}, "WRIT007.02": {"course_desc": "Writers on Writing", "offered": false, "url": "https://www.layuplist.com/course/3128", "distribs": ["LIT"]}, "WRIT007.03": {"course_desc": "Victorian Nightmares:Gothic", "offered": false, "url": "https://www.layuplist.com/course/3126", "distribs": ["LIT,", "W"]}, "WRIT007.04": {"course_desc": "Writing to Change the World", "offered": false, "url": "https://www.layuplist.com/course/3053", "distribs": ["SOC"]}, "WRIT007.05": {"course_desc": "Envrnment &amp; Devel in China", "offered": false, "url": "https://www.layuplist.com/course/3054", "distribs": ["INT,", "SOC,", "NW"]}, "WRIT007.06": {"course_desc": "Writing &amp; Reading the Iliad", "offered": false, "url": "https://www.layuplist.com/course/3125", "distribs": ["LIT"]}, "WRIT007.07": {"course_desc": "Originalty/Ownrshp of Ideas", "offered": false, "url": "https://www.layuplist.com/course/4167", "distribs": ["ART"]}, "WRIT007.13": {"course_desc": "Looks, Lookism and the Law", "offered": false, "url": "https://www.layuplist.com/course/4244", "distribs": ["TMV"]}, "WRIT007.14": {"course_desc": "Learning from Dartmouth", "offered": false, "url": "https://www.layuplist.com/course/3127", "distribs": ["ART,", "W"]}, "WRIT007.15": {"course_desc": "Anarchism", "offered": false, "url": "https://www.layuplist.com/course/3760", "distribs": ["LIT,", "W"]}, "WRIT007.16": {"course_desc": "What is a Discipline?", "offered": false, "url": "https://www.layuplist.com/course/3761", "distribs": ["SOC"]}, "WRIT007.17": {"course_desc": "Rituals of Transitions", "offered": false, "url": "https://www.layuplist.com/course/3762", "distribs": ["INT,", "CI"]}, "WRIT007.18": {"course_desc": "Writing Natural History", "offered": false, "url": "https://www.layuplist.com/course/3763", "distribs": ["SCI"]}, "WRIT007.19": {"course_desc": "The Stories We Tell", "offered": true, "url": "https://www.layuplist.com/course/4245", "distribs": ["LIT"]}, "WRIT007.20": {"course_desc": "Science of Healthy Eating", "offered": false, "url": "https://www.layuplist.com/course/4246", "distribs": ["SCI"]}, "WRIT007.21": {"course_desc": "Interrogating the News", "offered": false, "url": "https://www.layuplist.com/course/4247", "distribs": ["SOC"]}, "WRIT007.22": {"course_desc": "Technology and Sport", "offered": true, "url": "https://www.layuplist.com/course/4248", "distribs": ["TAS"]}, "WRIT007.23": {"course_desc": "The Art of the Interview", "offered": true, "url": "https://www.layuplist.com/course/4249", "distribs": ["SOC"]}, "WRIT007.24": {"course_desc": "Past Imperfect", "offered": true, "url": "https://www.layuplist.com/course/4250", "distribs": ["TMV"]}, "WRIT007.25": {"course_desc": "The Worlds Englishes", "offered": false, "url": "https://www.layuplist.com/course/4736", "distribs": ["INT,", "SOC"]}, "WRIT007.26": {"course_desc": "Jane Eyre and Vict. Culture", "offered": true, "url": "https://www.layuplist.com/course/4873", "distribs": ["LIT,", "W"]}, "WRIT007.27": {"course_desc": "Philosophy of Science", "offered": true, "url": "https://www.layuplist.com/course/4874", "distribs": ["TMV"]}, "WRIT007": {"course_desc": "First-year Seminar in Writing", "offered": false, "url": "https://www.layuplist.com/course/3012", "distribs": []}, "WRIT008": {"course_desc": "Writing with Media", "offered": false, "url": "https://www.layuplist.com/course/3013", "distribs": ["ART"]}, "WRIT009": {"course_desc": "Composition", "offered": false, "url": "https://www.layuplist.com/course/3014", "distribs": ["ART"]}, "WRIT010": {"course_desc": "Writing In The Workplace", "offered": false, "url": "https://www.layuplist.com/course/3015", "distribs": []}, "WRIT019": {"course_desc": "Multilingual Writing", "offered": true, "url": "https://www.layuplist.com/course/4875", "distribs": ["SOC"]}, "WRIT020": {"course_desc": "Rhetoric of Media Culture", "offered": false, "url": "https://www.layuplist.com/course/4737", "distribs": ["ART"]}, "WRIT041": {"course_desc": "Writing and Speaking Public Policy", "offered": true, "url": "https://www.layuplist.com/course/3016", "distribs": ["ART,", "W"]}, "WRIT042": {"course_desc": "The Art of Science Writing", "offered": false, "url": "https://www.layuplist.com/course/3017", "distribs": []}, "WRIT043": {"course_desc": "The Written Judicial Opinion", "offered": false, "url": "https://www.layuplist.com/course/3018", "distribs": ["SOC"]}, "WRIT044.01": {"course_desc": "Life Sciences Writing and Communication", "offered": true, "url": "https://www.layuplist.com/course/3020", "distribs": ["ART"]}, "WRIT044.02": {"course_desc": "Science and Technology Writing and Presentation", "offered": true, "url": "https://www.layuplist.com/course/3021", "distribs": ["ART"]}, "WRIT044": {"course_desc": "Writing and Science", "offered": false, "url": "https://www.layuplist.com/course/3019", "distribs": []}, "WRIT080": {"course_desc": "Independent Research", "offered": true, "url": "https://www.layuplist.com/course/3022", "distribs": []}}